infinilint/__init__.py
infinilint/__main__.py
infinilint/base.yml
infinilint-0.1.2.dist-info/DESCRIPTION.rst
infinilint-0.1.2.dist-info/METADATA
infinilint-0.1.2.dist-info/RECORD
infinilint-0.1.2.dist-info/WHEEL
infinilint-0.1.2.dist-info/entry_points.txt
infinilint-0.1.2.dist-info/metadata.json
infinilint-0.1.2.dist-info/top_level.txt
