Metadata-Version: 2.0
Name: infinilint
Version: 0.1.2
Summary: A configurable lint runner
Home-page: https://github.com/sophos/infinilint
Author: Brian Redmond
Author-email: brian.redmond@sophos.com
License: MIT
Keywords: infinilint lint development ci
Platform: UNKNOWN
Classifier: Development Status :: 3 - Alpha
Classifier: Intended Audience :: Developers
Classifier: Topic :: Software Development :: Build Tools
Classifier: License :: OSI Approved :: MIT License
Classifier: Programming Language :: Python :: 2
Classifier: Programming Language :: Python :: 2.7
Classifier: Programming Language :: Python :: 3
Classifier: Programming Language :: Python :: 3.3
Classifier: Programming Language :: Python :: 3.4
Classifier: Programming Language :: Python :: 3.5
Requires-Dist: docker
Requires-Dist: hiyapyco
Requires-Dist: requests
Requires-Dist: six
Requires-Dist: watchdog
